<?xml version="1.0" encoding="utf-8"?>
<!-- Created by ModBuddy on 12/26/2012 9:21:40 AM -->
<GameData>
	<IconTextureAtlases>
		<Row>
			<Atlas>CIV_COLOR_ATLAS_PLAT</Atlas>
			<IconSize>256</IconSize>
			<Filename>PlatAtlas256.dds</Filename>
			<IconsPerRow>4</IconsPerRow>
			<IconsPerColumn>1</IconsPerColumn>
		</Row>
		<Row>
			<Atlas>CIV_COLOR_ATLAS_PLAT</Atlas>
			<IconSize>214</IconSize>
			<Filename>PlatAtlas214.dds</Filename>
			<IconsPerRow>4</IconsPerRow>
			<IconsPerColumn>1</IconsPerColumn>
		</Row>
		<Row>
			<Atlas>CIV_COLOR_ATLAS_PLAT</Atlas>
			<IconSize>128</IconSize>
			<Filename>PlatAtlas128.dds</Filename>
			<IconsPerRow>4</IconsPerRow>
			<IconsPerColumn>1</IconsPerColumn>
		</Row>
		<Row>
			<Atlas>CIV_COLOR_ATLAS_PLAT</Atlas>
			<IconSize>80</IconSize>
			<Filename>PlatAtlas80.dds</Filename>
			<IconsPerRow>4</IconsPerRow>
			<IconsPerColumn>1</IconsPerColumn>
		</Row>
		<Row>
			<Atlas>CIV_COLOR_ATLAS_PLAT</Atlas>
			<IconSize>64</IconSize>
			<Filename>PlatAtlas64.dds</Filename>
			<IconsPerRow>4</IconsPerRow>
			<IconsPerColumn>1</IconsPerColumn>
		</Row>
		<Row>
			<Atlas>CIV_COLOR_ATLAS_PLAT</Atlas>
			<IconSize>45</IconSize>
			<Filename>PlatAtlas45.dds</Filename>
			<IconsPerRow>4</IconsPerRow>
			<IconsPerColumn>1</IconsPerColumn>
		</Row>
		<Row>
			<Atlas>CIV_COLOR_ATLAS_PLAT</Atlas>
			<IconSize>32</IconSize>
			<Filename>PlatAtlas32.dds</Filename>
			<IconsPerRow>4</IconsPerRow>
			<IconsPerColumn>1</IconsPerColumn>
		</Row>
		<Row>
			<Atlas>CIV_ALPHA_ATLAS_PLAT</Atlas>
			<Iconsize>32</Iconsize>
			<Filename>PlatAlphaAtlas32.dds</Filename>
			<IconsPerRow>4</IconsPerRow>
			<IconsPerColumn>1</IconsPerColumn>
		</Row>
	</IconTextureAtlases>

</GameData>